qapytest/__init__.py
qapytest/_attach.py
qapytest/_client_http.py
qapytest/_config.py
qapytest/_config_http.py
qapytest/_internal.py
qapytest/_json_validation.py
qapytest/_plugin.py
qapytest/_redis.py
qapytest/_report.py
qapytest/_soft_assert.py
qapytest/_sql.py
qapytest/_step.py
qapytest/py.typed
qapytest/_assets/_log_tree.html.jinja2
qapytest/_assets/report.html.jinja2
qapytest/_assets/scripts.js
qapytest/_assets/styles.css
qapytest-0.3.0.dist-info/METADATA
qapytest-0.3.0.dist-info/WHEEL
qapytest-0.3.0.dist-info/entry_points.txt
qapytest-0.3.0.dist-info/licenses/LICENSE
qapytest-0.3.0.dist-info/licenses/NOTICE
qapytest-0.3.0.dist-info/RECORD
