Metadata-Version: 2.4
Name: qapytest
Version: 0.3.0
Summary: A powerful testing framework based on pytest, specifically designed for QA engineers
Project-URL: Homepage, https://github.com/o73k51i/qapytest
Project-URL: Repository, https://github.com/o73k51i/qapytest
Project-URL: Documentation, https://github.com/o73k51i/qapytest/blob/main/README.md
Project-URL: Bug Reports, https://github.com/o73k51i/qapytest/issues
Author-email: o73k51i <o73k51i@proton.me>
License: MIT License
License-File: LICENSE
License-File: NOTICE
Keywords: automation,graphql,http,pytest,qa,redis,soft-assert,sql,test,testing
Classifier: Development Status :: 4 - Beta
Classifier: Framework :: Pytest
Classifier: Intended Audience :: Developers
Classifier: License :: OSI Approved :: MIT License
Classifier: Programming Language :: Python :: 3
Classifier: Programming Language :: Python :: 3.10
Classifier: Programming Language :: Python :: 3.11
Classifier: Programming Language :: Python :: 3.12
Classifier: Programming Language :: Python :: 3.13
Classifier: Topic :: Software Development :: Quality Assurance
Classifier: Topic :: Software Development :: Testing
Requires-Python: <3.14,>=3.10
Requires-Dist: faker>=37.11.0
Requires-Dist: httpx>=0.28.1
Requires-Dist: jinja2>=3.1.6
Requires-Dist: jsonschema>=4.25.1
Requires-Dist: pytest-playwright>=0.7.1
Requires-Dist: pytest>=8.4.2
Requires-Dist: python-dotenv>=1.1.1
Requires-Dist: redis>=6.4.0
Requires-Dist: sqlalchemy>=2.0.43
